LICENSE
MANIFEST.in
README.md
setup.cfg
setup.py
cron/__init__.py
cron/decorators.py
cron/helpers.py
cron/management/__init__.py
cron/management/commands/__init__.py
cron/management/commands/cron.py
podiant_cron.egg-info/PKG-INFO
podiant_cron.egg-info/SOURCES.txt
podiant_cron.egg-info/dependency_links.txt
podiant_cron.egg-info/not-zip-safe
podiant_cron.egg-info/requires.txt
podiant_cron.egg-info/top_level.txt